hip_online_store/__init__.py
hip_online_store/ponyta/client.py
hip_online_store/ponyta/common/__init__.py
hip_online_store/ponyta/common/request_utils.py
hip_online_store/ponyta/core/__init__.py
hip_online_store/ponyta/core/config.py
hip_online_store/ponyta/online_store/_ponyta_online_store_client.py
hip_online_store/ponyta/registry/__init__.py
hip_online_store/ponyta/registry/_ponyta_registry_client.py
hip_online_store-0.2.13.dist-info/METADATA
hip_online_store-0.2.13.dist-info/WHEEL
hip_online_store-0.2.13.dist-info/RECORD
